sudokuPackage/__init__.py
sudokuPackage/main.py
sudokuPackage/Sudoku_Show/Generate.py
sudokuPackage/Sudoku_Show/__init__.py
sudokuPackage/Sudoku_Show/paint.py
sudokuPackage/Sudoku_Solve/Game_Sudoku.py
sudokuPackage/Sudoku_Solve/__init__.py
sudokuPackage/Sudoku_Solve/configs.py
sudokuPackage-0.1.dist-info/LICENSE.txt
sudokuPackage-0.1.dist-info/METADATA
sudokuPackage-0.1.dist-info/WHEEL
sudokuPackage-0.1.dist-info/top_level.txt
sudokuPackage-0.1.dist-info/RECORD
