Metadata-Version: 2.1
Name: sudokuPackage
Version: 0.1
Summary: A sudoku game
Home-page: https://github.com/7lu0420/TravisCI-DATA533
Author: Shveta Sharma & Tia Wang
Author-email: yingziwang0308@gmail.com
License: MIT
Platform: UNKNOWN
License-File: LICENSE.txt
